{
  "categorySlug": "telitett-rudfa",
  "name": "Telített rúdfa Ø120mm",
  "slug": "telitett-rudfa-atmero-120",
  "meta": {
    "title": "Telített rúdfa 120 mm – Masszív kültéri fa | Elvira Tüzép",
    "description": "Masszív, tartós telített rúdfa 120 mm átmérővel. Ideális hintaállványhoz, kerítéshez és nagyobb kerti szerkezetekhez.",
    "image": "/termekkep/telitett-rudfa-atmero-12.webp"
  },
  "description": "Prémium minőségű, nyomás alatt impregnált telített rúdfa 120 mm átmérővel.",
  "longDescription": "A telített rúdfa 120 mm-es átmérővel alkalmas szerkezeti célokra és nagy igénybevételre.",
  "longDescription2": "Játszótéri szerkezeteknél, hintaállványoknál és terhelhető kerti projektekben is bevált.",
  "longDescription3": "",
  "material": "Nagy nyomáson telített borovi fenyő",
  "audience": [
    "kertépítők",
    "játszótér-építők",
    "kivitelezők"
  ],
  "blogtags": [
    "kertifa",
    "rúdfa"
  ],
  "specs": {
    "1c1af9e3f3": {
      "label": "Átmérő",
      "order": 1,
      "value": "120 mm"
    },
    "1a7cda36a2": {
      "label": "Hossz",
      "order": 2,
      "value": "500–4000 mm"
    },
    "b9319ea0b6": {
      "label": "Anyag",
      "order": 3,
      "value": "Nagynyomáson telített borovi fenyő"
    },
    "76d82efd49": {
      "label": "Kivitel",
      "order": 4,
      "value": "Körmart, erős kivitel"
    },
    "8d571f0020": {
      "label": "Impregnálás",
      "order": 5,
      "value": "Nyomás alatti (réz-bázisú)"
    },
    "234effd3c6": {
      "label": "Tömeg",
      "order": 6,
      "value": "≈ 10–15 kg/db"
    },
    "c3cfe595c8": {
      "label": "Felhasználás",
      "order": 7,
      "value": "Hintaállvány, szerkezeti elem, kerítés"
    },
    "6616a99e05": {
      "label": "Megjegyzés",
      "order": 8,
      "value": "Nagy teherbíráshoz ajánlott"
    }
  },
  "shippingDetails": {
    "weight": 28,
    "length": 400,
    "width": 12,
    "height": 12
  },
  "aggregateRating": {
    "@type": "AggregateRating",
    "ratingValue": 4.84,
    "reviewCount": 67
  },
  "image": "/termekkep/telitett-rudfa-atmero-12.webp",
  "images": [],
  "variants": [
    {
      "id": "variant_01KA93D309KB9P2E6CTPKWH0QG",
      "title": "Ø120mm x 50 | rúdfa",
      "sku": "RF1250",
      "variant_rank": 0,
      "price": 3760,
      "mprice": null,
      "m2price": null,
      "m3price": null,
      "palprice": null,
      "discountPrice": null,
      "discountPercent": null,
      "discountValidUntil": null,
      "stock": 0,
      "weight": 4,
      "length": 50,
      "width": 12,
      "height": 12
    },
    {
      "id": "variant_01KA93D63E632A41JJW7Z93E15",
      "title": "Ø120mm x 150 | rúdfa",
      "sku": "RF12150",
      "variant_rank": 1,
      "price": 6096,
      "mprice": null,
      "m2price": null,
      "m3price": null,
      "palprice": null,
      "discountPrice": null,
      "discountPercent": null,
      "discountValidUntil": null,
      "stock": 0,
      "weight": 12,
      "length": 150,
      "width": 12,
      "height": 12
    },
    {
      "id": "variant_01KA933XY2NV8TNF79DP5NTNTA",
      "title": "Ø120mm x 200 | rúdfa",
      "sku": "RF12200",
      "variant_rank": 2,
      "price": 7265,
      "mprice": null,
      "m2price": null,
      "m3price": null,
      "palprice": null,
      "discountPrice": null,
      "discountPercent": null,
      "discountValidUntil": null,
      "stock": 0,
      "weight": 14,
      "length": 200,
      "width": 12,
      "height": 12
    },
    {
      "id": "variant_01KA93D9695VSR1HB4HTY5921S",
      "title": "Ø120mm x 250 | rúdfa",
      "sku": "RF12250",
      "variant_rank": 3,
      "price": 9690,
      "mprice": null,
      "m2price": null,
      "m3price": null,
      "palprice": null,
      "discountPrice": null,
      "discountPercent": null,
      "discountValidUntil": null,
      "stock": 1,
      "weight": 18,
      "length": 250,
      "width": 12,
      "height": 12
    },
    {
      "id": "variant_01KA93DD9JE76Y75Y8ERYHB34V",
      "title": "Ø120mm x 300 | rúdfa",
      "sku": "RF12300",
      "variant_rank": 4,
      "price": 12192,
      "mprice": null,
      "m2price": null,
      "m3price": null,
      "palprice": null,
      "discountPrice": null,
      "discountPercent": null,
      "discountValidUntil": null,
      "stock": 1,
      "weight": 20,
      "length": 300,
      "width": 12,
      "height": 12
    },
    {
      "id": "variant_01KA93DHAX802QHK198TJMKWSF",
      "title": "Ø120mm x 400 | rúdfa",
      "sku": "RF12400",
      "variant_rank": 5,
      "price": 18515,
      "mprice": null,
      "m2price": null,
      "m3price": null,
      "palprice": null,
      "discountPrice": null,
      "discountPercent": null,
      "discountValidUntil": null,
      "stock": 0,
      "weight": 28,
      "length": 400,
      "width": 12,
      "height": 12
    }
  ],
  "stock": 2,
  "priceFrom": 3760,
  "priceTo": 18515,
  "discountPercent": null,
  "discountValidUntil": null,
  "hasDiscount": false
}
