{
  "categorySlug": "telitett-felcolop",
  "items": [
    {
      "slug": "telitett-felcolop-atmero-70",
      "categorySlug": "telitett-felcolop",
      "name": "Telített félcölöp Ø70mm",
      "image": "/termekek/telitett-felcolop-atmero-7.webp",
      "images": [],
      "sku": "Telített félcölöp Ø70mm",
      "priceFrom": 1778,
      "priceTo": null,
      "discountPercent": null,
      "discountValidUntil": null,
      "stock": 1,
      "inStock": true,
      "hasVariants": false,
      "variantCount": 0,
      "ratingValue": 4.83,
      "reviewCount": 48
    }
  ]
}
